searchium/__init__.py
searchium/client/__init__.py
searchium/client/func.py
searchium/client/init.py
searchium/fvs/__init__.py
searchium/fvs/client.py
searchium/fvs/model.py
searchium-0.0.1rc5.dist-info/METADATA
searchium-0.0.1rc5.dist-info/WHEEL
searchium-0.0.1rc5.dist-info/RECORD
